fderiv/__init__.py
fderiv/fderiv.py
fderiv-0.1.2.dist-info/METADATA
fderiv-0.1.2.dist-info/WHEEL
fderiv-0.1.2.dist-info/top_level.txt
fderiv-0.1.2.dist-info/RECORD
