Metadata-Version: 2.1
Name: fderiv
Version: 0.1.2
Summary: Five point derivatives
Home-page: UNKNOWN
Author: Sudhanva Lalit
Author-email: sudsid@gmail.com
License: UNKNOWN
Platform: UNKNOWN
Classifier: Programming Language :: Python :: 3
Classifier: License :: OSI Approved :: MIT License
Classifier: Operating System :: OS Independent
Requires-Python: >=3.6
